{"playerID":2,"civilizationName":"seyyed","personalMapID":3,"citiesID":[],"workingTilesID":[],"unitsID":[2522],"worksID":[],"notificationsID":[],"numberOfEachResourceID":{},"numberOfEachExchangedResourceID":{},"civilizationNotUsableUnitsID":["Archer","ChariotArcher","Scout","Settler","Spearman","Warrior","Worker","Catapult","Horseman","Swordsman","Crossbowman","Knight","Longswordsman","Pikeman","Trebuchet","Canon","Cavalry","Lancer","Musketman","Rifleman","AntiTankGun","Artillery","Infantry","Panzer","Tank"],"civilizationUsableUnitsID":[],"civilizationResearchedTechnologiesID":{"Agriculture":2523},"civilizationNotResearchedTechnologiesID":{"ScientificTheory":2549,"HorsebackRiding":2564,"Combustion":2528,"Acoustics":2529,"Biology":2541,"Mathematics":2546,"Machinery":2552,"CivilService":2561,"Mining":2562,"IronWorking":2563,"Archaeology":2532,"Engineering":2559,"Dynamite":2544,"Electricity":2556,"Education":2555,"ReplaceableParts":2534,"Archery":2530,"Currency":2551,"Pottery":2557,"PrintingPress":2537,"Gunpowder":2525,"Rifling":2535,"Economics":2526,"Theology":2538,"Telegraph":2533,"Construction":2553,"Railroad":2566,"Calendar":2542,"AnimalHusbandry":2543,"Banking":2560,"Radio":2558,"Masonry":2545,"Steel":2567,"Physics":2547,"Fertilize":2565,"Trapping":2531,"Chemistry":2548,"MetalCasting":2554,"Chivalry":2569,"MilitaryScience":2540,"SteamPower":2550,"TheWheel":2568,"Writing":2524,"BronzeWorking":2536,"Metallurgy":2539,"Philosophy":2527},"numberOfBeakers":100,"gold":400,"happiness":0,"happiness0":10,"happinessPerLuxuryResource":4,"unitMaintenanceCost":2,"roadMaintenanceCost":1,"railMaintenanceCost":1,"turn":0,"id":1}